quandl/__init__.py
quandl/api_config.py
quandl/bulkdownload.py
quandl/connection.py
quandl/export_table.py
quandl/get.py
quandl/get_point_in_time.py
quandl/get_table.py
quandl/message.py
quandl/util.py
quandl/version.py
quandl/errors/__init__.py
quandl/errors/quandl_error.py
quandl/model/__init__.py
quandl/model/data.py
quandl/model/data_list.py
quandl/model/data_mixin.py
quandl/model/database.py
quandl/model/dataset.py
quandl/model/datatable.py
quandl/model/merged_data_list.py
quandl/model/merged_dataset.py
quandl/model/model_base.py
quandl/model/model_list.py
quandl/model/paginated_list.py
quandl/model/point_in_time.py
quandl/operations/__init__.py
quandl/operations/data_list.py
quandl/operations/get.py
quandl/operations/list.py
quandl/operations/operation.py
quandl/utils/__init__.py
quandl/utils/api_key_util.py
quandl/utils/request_type_util.py
Quandl-3.7.0.dist-info/LICENSE.txt
Quandl-3.7.0.dist-info/METADATA
Quandl-3.7.0.dist-info/WHEEL
Quandl-3.7.0.dist-info/top_level.txt
Quandl-3.7.0.dist-info/RECORD
