Metadata-Version: 2.1
Name: Quandl
Version: 3.7.0
Summary: Package for quandl API access
Home-page: https://github.com/quandl/quandl-python
Author: Quandl
Author-email: connect@quandl.com
Maintainer: Quandl Development Team
Maintainer-email: connect@quandl.com
License: MIT
Keywords: quandl,API,data,financial,economic
Platform: UNKNOWN
Classifier: Intended Audience :: Developers
Classifier: License :: OSI Approved :: MIT License
Classifier: Operating System :: OS Independent
Classifier: Programming Language :: Python :: 3.6
Classifier: Programming Language :: Python :: 3.7
Classifier: Programming Language :: Python :: 3.8
Requires-Python: >= 3.6
License-File: LICENSE.txt
